CHANGELOG.md
templa/__init__.py
templa/builder.py
templa/config.py
templa/py.typed
templa/yaml_builder.py
templa-1.0.0.dist-info/LICENSE
templa-1.0.0.dist-info/METADATA
templa-1.0.0.dist-info/WHEEL
templa-1.0.0.dist-info/RECORD
