Metadata-Version: 2.1
Name: templa
Version: 1.0.0
Summary: Building system using Jinja2 templates for your code.
Home-page: https://github.com/yuxki/templa
License: MIT
Author: yuxki
Author-email: yuxki.ryoshi@gmail.com
Requires-Python: >=3.8,<4.0
Classifier: License :: OSI Approved :: MIT License
Classifier: Programming Language :: Python :: 3
Classifier: Programming Language :: Python :: 3.8
Classifier: Programming Language :: Python :: 3.9
Classifier: Programming Language :: Python :: 3.10
Classifier: Programming Language :: Python :: 3.11
Requires-Dist: jinja2 (==3.1.2)
Requires-Dist: pyyaml (==6.0)
Project-URL: Documentation, https://templa.readthedocs.io/en/latest/index.html
